LICENSE.txt
README.rst
setup.py
swagger_to/__init__.py
swagger_to/elm_client.py
swagger_to/go_server.py
swagger_to/indent.py
swagger_to/intermediate.py
swagger_to/py.typed
swagger_to/py_client.py
swagger_to/style.py
swagger_to/swagger.py
swagger_to/swaggerjsonschema.py
swagger_to/ts_angular5_client.py
swagger_to.egg-info/PKG-INFO
swagger_to.egg-info/SOURCES.txt
swagger_to.egg-info/dependency_links.txt
swagger_to.egg-info/entry_points.txt
swagger_to.egg-info/requires.txt
swagger_to.egg-info/top_level.txt
swagger_to/bin/__init__.py
swagger_to/bin/swagger_style.py
swagger_to/bin/swagger_to_elm_client.py
swagger_to/bin/swagger_to_go_server.py
swagger_to/bin/swagger_to_py_client.py
swagger_to/bin/swagger_to_ts_angular5_client.py