Metadata-Version: 2.1
Name: swagger-to
Version: 5.0.0
Summary: Generate server and client code from Swagger (OpenAPI 2.0) specification
Home-page: https://github.com/Parquery/swagger-to
Author: Marko Ristin
Author-email: marko@parquery.com
License: License :: OSI Approved :: MIT License
Keywords: swagger code generation python elm go typescript server client angular
Classifier: Development Status :: 5 - Production/Stable
Classifier: Intended Audience :: Developers
Classifier: License :: OSI Approved :: MIT License
Classifier: Programming Language :: Python :: 3.7
Classifier: Programming Language :: Python :: 3.8
Classifier: Programming Language :: Python :: 3.9
Classifier: Programming Language :: Python :: 3.10
Provides-Extra: dev
License-File: LICENSE.txt
